{
    "advertisements": [
        {
            "description": "3 BHK, price: 50,00,000 INR, Placeholder description.",
            "lat": 12.81425118669924,
            "lng": 78.03008188248559,
            "name": "Placeholder Apartment 0"
        },
        {
            "description": "3 BHK, price: 50,00,000 INR, Placeholder description.",
            "lat": 12.964873902795366,
            "lng": 77.46524205467308,
            "name": "Placeholder Apartment 1"
        },
        {
            "description": "3 BHK, price: 50,00,000 INR, Placeholder description.",
            "lat": 12.984999351773672,
            "lng": 77.80929835773422,
            "name": "Placeholder Apartment 2"
        },
        {
            "description": "3 BHK, price: 50,00,000 INR, Placeholder description.",
            "lat": 12.72005319756845,
            "lng": 77.93534129902862,
            "name": "Placeholder Apartment 3"
        },
        {
            "description": "3 BHK, price: 50,00,000 INR, Placeholder description.",
            "lat": 13.10034630233923,
            "lng": 78.09483280139824,
            "name": "Placeholder Apartment 4"
        },
        {
            "description": "3 BHK, price: 50,00,000 INR, Placeholder description.",
            "lat": 13.110995312875485,
            "lng": 77.78552398351295,
            "name": "Placeholder Apartment 5"
        },
        {
            "description": "3 BHK, price: 50,00,000 INR, Placeholder description.",
            "lat": 12.455519105105196,
            "lng": 77.71890493359255,
            "name": "Placeholder Apartment 6"
        },
        {
            "description": "3 BHK, price: 50,00,000 INR, Placeholder description.",
            "lat": 13.41255579377928,
            "lng": 77.28494334441396,
            "name": "Placeholder Apartment 7"
        },
        {
            "description": "3 BHK, price: 50,00,000 INR, Placeholder description.",
            "lat": 12.93171656591618,
            "lng": 77.75500180445356,
            "name": "Placeholder Apartment 8"
        },
        {
            "description": "3 BHK, price: 50,00,000 INR, Placeholder description.",
            "lat": 12.90878343076258,
            "lng": 77.68319457412936,
            "name": "Placeholder Apartment 9"
        },
        {
            "description": "3 BHK, price: 50,00,000 INR, Placeholder description.",
            "lat": 12.746445172997387,
            "lng": 77.53707282832984,
            "name": "Placeholder Apartment 0"
        },
        {
            "description": "3 BHK, price: 50,00,000 INR, Placeholder description.",
            "lat": 12.80155499375974,
            "lng": 77.14745848049716,
            "name": "Placeholder Apartment 1"
        },
        {
            "description": "3 BHK, price: 50,00,000 INR, Placeholder description.",
            "lat": 12.721924955627125,
            "lng": 77.54858703345201,
            "name": "Placeholder Apartment 2"
        },
        {
            "description": "3 BHK, price: 50,00,000 INR, Placeholder description.",
            "lat": 13.218045674080303,
            "lng": 78.01428262572078,
            "name": "Placeholder Apartment 0"
        },
        {
            "description": "3 BHK, price: 50,00,000 INR, Placeholder description.",
            "lat": 13.109925048731819,
            "lng": 77.41431177941718,
            "name": "Placeholder Apartment 0"
        },
        {
            "description": "3 BHK, price: 50,00,000 INR, Placeholder description.",
            "lat": 13.108401997226709,
            "lng": 77.95960660770253,
            "name": "Placeholder Apartment 1"
        },
        {
            "description": "3 BHK, price: 50,00,000 INR, Placeholder description.",
            "lat": 13.212054577199913,
            "lng": 77.73114096559145,
            "name": "Placeholder Apartment 2"
        },
        {
            "description": "3 BHK, price: 50,00,000 INR, Placeholder description.",
            "lat": 12.489389981794837,
            "lng": 77.28302701869026,
            "name": "Placeholder Apartment 3"
        },
        {
            "description": "3 BHK, price: 50,00,000 INR, Placeholder description.",
            "lat": 13.05043154210352,
            "lng": 77.75325141053374,
            "name": "Placeholder Apartment 4"
        },
        {
            "description": "3 BHK, price: 50,00,000 INR, Placeholder description.",
            "lat": 12.772811539216207,
            "lng": 77.34278487733239,
            "name": "Placeholder Apartment 5"
        },
        {
            "description": "3 BHK, price: 50,00,000 INR, Placeholder description.",
            "lat": 13.04277937546943,
            "lng": 77.7592135603195,
            "name": "Placeholder Apartment 6"
        },
        {
            "description": "3 BHK, price: 50,00,000 INR, Placeholder description.",
            "lat": 12.543683822911172,
            "lng": 77.54171493856475,
            "name": "Placeholder Apartment 7"
        },
        {
            "description": "3 BHK, price: 50,00,000 INR, Placeholder description.",
            "lat": 13.123204264097337,
            "lng": 78.0569859740694,
            "name": "Placeholder Apartment 8"
        },
        {
            "description": "3 BHK, price: 50,00,000 INR, Placeholder description.",
            "lat": 12.453153268329554,
            "lng": 78.08099733353082,
            "name": "Placeholder Apartment 0"
        },
        {
            "description": "3 BHK, price: 50,00,000 INR, Placeholder description.",
            "lat": 12.544880947805472,
            "lng": 77.4360992648147,
            "name": "Placeholder Apartment 1"
        },
        {
            "description": "3 BHK, price: 50,00,000 INR, Placeholder description.",
            "lat": 13.265384403817825,
            "lng": 77.26828907682852,
            "name": "Placeholder Apartment 2"
        },
        {
            "description": "3 BHK, price: 50,00,000 INR, Placeholder description.",
            "lat": 12.855088191553573,
            "lng": 77.8394666909276,
            "name": "Placeholder Apartment 3"
        },
        {
            "description": "3 BHK, price: 50,00,000 INR, Placeholder description.",
            "lat": 12.763270696058347,
            "lng": 77.2842557254493,
            "name": "Placeholder Apartment 4"
        },
        {
            "description": "3 BHK, price: 50,00,000 INR, Placeholder description.",
            "lat": 12.782310147755057,
            "lng": 77.86198796357482,
            "name": "Placeholder Apartment 5"
        },
        {
            "description": "3 BHK, price: 50,00,000 INR, Placeholder description.",
            "lat": 12.73307668330418,
            "lng": 77.98585317168936,
            "name": "Placeholder Apartment 6"
        },
        {
            "description": "3 BHK, price: 50,00,000 INR, Placeholder description.",
            "lat": 12.773485032844913,
            "lng": 77.6949333220452,
            "name": "Placeholder Apartment 7"
        },
        {
            "description": "3 BHK, price: 50,00,000 INR, Placeholder description.",
            "lat": 12.88774275074191,
            "lng": 77.12138733155693,
            "name": "Placeholder Apartment 0"
        },
        {
            "description": "3 BHK, price: 50,00,000 INR, Placeholder description.",
            "lat": 13.395991617384096,
            "lng": 77.9355843876414,
            "name": "Placeholder Apartment 1"
        },
        {
            "description": "3 BHK, price: 50,00,000 INR, Placeholder description.",
            "lat": 12.875108703588817,
            "lng": 77.49442397910363,
            "name": "Placeholder Apartment 0"
        },
        {
            "description": "3 BHK, price: 50,00,000 INR, Placeholder description.",
            "lat": 12.942134022554061,
            "lng": 77.6117398835927,
            "name": "Placeholder Apartment 0"
        },
        {
            "description": "3 BHK, price: 50,00,000 INR, Placeholder description.",
            "lat": 13.215543584836599,
            "lng": 77.99434864521352,
            "name": "Placeholder Apartment 1"
        },
        {
            "description": "3 BHK, price: 50,00,000 INR, Placeholder description.",
            "lat": 13.24480862631659,
            "lng": 77.505811466428,
            "name": "Placeholder Apartment 2"
        },
        {
            "description": "3 BHK, price: 50,00,000 INR, Placeholder description.",
            "lat": 12.455075435711862,
            "lng": 77.97089240495976,
            "name": "Placeholder Apartment 3"
        },
        {
            "description": "3 BHK, price: 50,00,000 INR, Placeholder description.",
            "lat": 12.642094111979974,
            "lng": 77.94940568611499,
            "name": "Placeholder Apartment 4"
        },
        {
            "description": "3 BHK, price: 50,00,000 INR, Placeholder description.",
            "lat": 12.993871069060283,
            "lng": 77.72596088768425,
            "name": "Placeholder Apartment 0"
        }
    ],
    "heatmaps": [
        {
            "details": [
                {
                    "geometry": {
                        "location": {
                            "lat": 12.9351711,
                            "lng": 77.6214199
                        },
                        "viewport": {
                            "northeast": {
                                "lat": 12.9364468302915,
                                "lng": 77.62271013029151
                            },
                            "southwest": {
                                "lat": 12.9337488697085,
                                "lng": 77.6200121697085
                            }
                        }
                    },
                    "icon": "https://maps.gstatic.com/mapfiles/place_api/icons/school-71.png",
                    "id": "5fa2bfc9fab9c0b85e74f87fa524ad073907e481",
                    "name": "Eurokids Koramangala",
                    "opening_hours": {
                        "open_now": true,
                        "weekday_text": []
                    },
                    "photos": [
                        {
                            "height": 3168,
                            "html_attributions": [
                                "<a href=\"https://maps.google.com/maps/contrib/110390727899426236256/photos\">EuroKids Koramangala, Bangalore</a>"
                            ],
                            "photo_reference": "CmRaAAAA_Uik7G7EiExEH91vRss4wGr7QtqUOzLujCfCnus45FSBgaHISntWiDDTVQLvx-9liW94IpeLcS9PJayX07v4YN0mNTl7WEaOlnm7rArkTEO62-sEjV6LnoNJF1yfFrkMEhC5V24jHBJcfKVDWeqrbBIYGhQZa8E56KJfT5mTtdDDrj65XSJoWA",
                            "width": 4752
                        }
                    ],
                    "place_id": "ChIJVWZELkUUrjsRYBx0z0hRtlo",
                    "rating": 4.7,
                    "reference": "CmRRAAAAunGridj4_vRohMpFomJQOumFoBjj_88MAL5WNVX62zWvkYau9fQt2JUgd6nVD4muXi5hlBeRyWk0au-scTNnExgSON3gDREWFYyUQ4OMRaSTkk_NayhWtDXWofQ53UWlEhDeCFmy-XT8PH0eWEnY-zWHGhQsPZo85YmOMcDaxjPXu1vrvy9syA",
                    "scope": "GOOGLE",
                    "types": [
                        "school",
                        "point_of_interest",
                        "establishment"
                    ],
                    "vicinity": "# 73, 17th B, Main, 3rd Cross,, 5th Block Koramangala, Bengaluru"
                },
                {
                    "geometry": {
                        "location": {
                            "lat": 12.9406589,
                            "lng": 77.6207459
                        },
                        "viewport": {
                            "northeast": {
                                "lat": 12.9421399302915,
                                "lng": 77.62205883029151
                            },
                            "southwest": {
                                "lat": 12.9394419697085,
                                "lng": 77.6193608697085
                            }
                        }
                    },
                    "icon": "https://maps.gstatic.com/mapfiles/place_api/icons/school-71.png",
                    "id": "ec23b1a953165a898c8fc0d560e13fe1ae1ded99",
                    "name": "Bethany High School",
                    "opening_hours": {
                        "open_now": true,
                        "weekday_text": []
                    },
                    "photos": [
                        {
                            "height": 400,
                            "html_attributions": [
                                "<a href=\"https://maps.google.com/maps/contrib/105385867378595300605/photos\">Bethany High School</a>"
                            ],
                            "photo_reference": "CmRaAAAAV_1hwnkYDWstgxLGseWdxOpOnBcy9B6NrV-MyXRzSqaQrmCyxKja3J48FSSEE0DoNHjb0n04wlijtIFs30B4EaTzVnKKOz6DIHrv779S85VN1h7u_AIwmSslpkn5zfC9EhA9FOwvNScwnogYJ8CcmSjAGhTjFgKzaWpdfEQV5u1EpYRf6Q4jww",
                            "width": 402
                        }
                    ],
                    "place_id": "ChIJJ7jAc0YUrjsRvQuaf7GlZdM",
                    "rating": 4,
                    "reference": "CmRSAAAAkci-L1DmUVegNqAlYAqDTNwg5wvr3SNUTcmwcy4uBVcQ0m_3SZcVupEYJH4t8JE0AKuJddNDwfDXmXx-C_q8-lUuoJ8WGS0Ss7PD-2pkTKw5Q0jNmYQ_RxSFt-yG7LHfEhDB0dhNL48CszYYonsSZeylGhTluFU33JxRmDC_y1fTQLuQhkXNKw",
                    "scope": "GOOGLE",
                    "types": [
                        "school",
                        "point_of_interest",
                        "establishment"
                    ],
                    "vicinity": "CA -12, 20th Main, Koramangala, Next to Koramangala Police station, Bengaluru"
                },
                {
                    "geometry": {
                        "location": {
                            "lat": 12.939947,
                            "lng": 77.61590029999999
                        },
                        "viewport": {
                            "northeast": {
                                "lat": 12.9413288302915,
                                "lng": 77.61720463029151
                            },
                            "southwest": {
                                "lat": 12.9386308697085,
                                "lng": 77.61450666970849
                            }
                        }
                    },
                    "icon": "https://maps.gstatic.com/mapfiles/place_api/icons/school-71.png",
                    "id": "ad24e5f1cb732b348d0df5ab0daae92be2e09d1f",
                    "name": "Lawrence School SSLC",
                    "photos": [
                        {
                            "height": 1152,
                            "html_attributions": [
                                "<a href=\"https://maps.google.com/maps/contrib/100606137110309137162/photos\">Mohammed Hafeezurrahaman</a>"
                            ],
                            "photo_reference": "CmRaAAAAVMcj9IyDuDJ81dqdMkOFpnxRTJNOM9eBk4gggfBPMoR7FDjJQa_StggC7Fibb8RmLngmBjs_xIP16NRN0iI-EIXaKmwoqnj2psuyIgjgwVcv_rYMAHanA3RI0gSOVeGmEhDJwSeFTIgvJ_qqGJ0BizfxGhSfk4d-uru_KdkvJkD8x80WSr0dYQ",
                            "width": 2048
                        }
                    ],
                    "place_id": "ChIJK8BZqFsUrjsRw5st5Q8PUhI",
                    "rating": 3.8,
                    "reference": "CmRRAAAAu2U8fGpp9m1r0jTibf32OG8p8dnkXzn-zpLYCTX3TssZ-i_OsnzROXd9YP2Uer48-Ib0Ni0CsUto9dlPhkbhgiqR0xBWu-cut_sskvmTE4ixcJCRGwOKEgGqsQR0bPIhEhCKW43l9iGsdqV-VH8rfG1JGhRlb6GXfBMuvFnQ6wlDZqiVUMjjVw",
                    "scope": "GOOGLE",
                    "types": [
                        "school",
                        "point_of_interest",
                        "establishment"
                    ],
                    "vicinity": "#315, 8th Block, 2nd C Main, Koramangala, Koramangala, Bengaluru"
                },
                {
                    "geometry": {
                        "location": {
                            "lat": 12.9364091,
                            "lng": 77.6209928
                        },
                        "viewport": {
                            "northeast": {
                                "lat": 12.9377515302915,
                                "lng": 77.62233718029151
                            },
                            "southwest": {
                                "lat": 12.9350535697085,
                                "lng": 77.6196392197085
                            }
                        }
                    },
                    "icon": "https://maps.gstatic.com/mapfiles/place_api/icons/school-71.png",
                    "id": "37105f29d41e9d9c86f80f362b6c5956562e076b",
                    "name": "TLC Montessori Preschool",
                    "opening_hours": {
                        "open_now": true,
                        "weekday_text": []
                    },
                    "photos": [
                        {
                            "height": 800,
                            "html_attributions": [
                                "<a href=\"https://maps.google.com/maps/contrib/106879523851195133426/photos\">TLC Montessori Preschool</a>"
                            ],
                            "photo_reference": "CmRaAAAAbLfbuy9daRq2bsps2P-ckzCpcZo67phFcW-uRj19GA6XCQDfFX3ckc0808JwfToQgkYvuw85M4QT44WKxVrkCCCj8WnwWGuKl8JutJI8TYN7fI_9fjdu6kSNwqLOFOFfEhBAdZalHIDOrp7FpxibAZqoGhQjIB9Spyp6AHj-cvwuh2Nbb8Z-4A",
                            "width": 1280
                        }
                    ],
                    "place_id": "ChIJWUnSEEUUrjsRDoivDZlsf6c",
                    "rating": 5,
                    "reference": "CmRSAAAAxXA43YN7U1IKPSedqx-7HHIie7TD8xn-gAmU_BhNSDNtl6WhgOoIGGNI5C-tH_5no0oEIY2WXh-EMrxFTFDOt3pOPAv6VL2nM89Q0P1TZ_iowh-YP2CR8Yxg_qZjpexvEhBxHNJgddunk7wxllSiTCloGhS2FUu3QAxWgtAbpAR4inR-Swu7KA",
                    "scope": "GOOGLE",
                    "types": [
                        "school",
                        "point_of_interest",
                        "establishment"
                    ],
                    "vicinity": "No. 56, Raj Villa, Near Cradle Hospital, Next To Oye Amritsar, 5th Cross, 6th Block, 60 Feet Road, Koramangala, Bengaluru"
                },
                {
                    "geometry": {
                        "location": {
                            "lat": 12.9357491,
                            "lng": 77.6248006
                        },
                        "viewport": {
                            "northeast": {
                                "lat": 12.9370515802915,
                                "lng": 77.6261898802915
                            },
                            "southwest": {
                                "lat": 12.9343536197085,
                                "lng": 77.6234919197085
                            }
                        }
                    },
                    "icon": "https://maps.gstatic.com/mapfiles/place_api/icons/school-71.png",
                    "id": "514ba86e0315a9dff442c4fd946078686b8e561c",
                    "name": "Little Feat",
                    "photos": [
                        {
                            "height": 3456,
                            "html_attributions": [
                                "<a href=\"https://maps.google.com/maps/contrib/116654763226944073154/photos\">Monnet Photography</a>"
                            ],
                            "photo_reference": "CmRaAAAATDPlRAxInMeqIoCaE-ERIjS7B4Wo3pkaKapnFUWFF5dweAvK9MDUXu7sL4fEH5_q_6UGhU_D5ALm4omJHaXFsWoerdGBuVlY0cfbj89v4HLzu5_yOcTYkv5tfi1VTPVKEhBfOaL5vEMXDhxs1I5HvkBrGhQ_mYZBHRFZ3lsKDrJVhK1Gxc7n0A",
                            "width": 5184
                        }
                    ],
                    "place_id": "ChIJE8R9PncWrjsRuoG_hXHVZbc",
                    "rating": 4.9,
                    "reference": "CmRSAAAAkVAc3-jg-34vIe9GC6_W9Jqb72dcbg7xq27q46yvET3X_wBvCWaRsciwIqw3pF2JdL8E1LkhJEaxsHcfv4WfJOa2J2AwtCmxTih-jppU5doowk6-1M4GO3aPmQr58gfGEhD7PtiGa-KzynapwUkXPeN0GhTjb6JBbvb7lxr2h15acpUpPBjv9A",
                    "scope": "GOOGLE",
                    "types": [
                        "school",
                        "point_of_interest",
                        "establishment"
                    ],
                    "vicinity": "42, 100 Feet Road, 6th Block, Ejipura, Bengaluru"
                },
                {
                    "geometry": {
                        "location": {
                            "lat": 12.9355728,
                            "lng": 77.6152633
                        },
                        "viewport": {
                            "northeast": {
                                "lat": 12.9370040802915,
                                "lng": 77.6166968802915
                            },
                            "southwest": {
                                "lat": 12.9343061197085,
                                "lng": 77.6139989197085
                            }
                        }
                    },
                    "icon": "https://maps.gstatic.com/mapfiles/place_api/icons/atm-71.png",
                    "id": "03c3946fd838b6518458dba29d5a54bcddb7169d",
                    "name": "HDFC Bank ATM",
                    "opening_hours": {
                        "open_now": true,
                        "weekday_text": []
                    },
                    "photos": [
                        {
                            "height": 1080,
                            "html_attributions": [
                                "<a href=\"https://maps.google.com/maps/contrib/103376485048052780343/photos\">Kumar Vishal</a>"
                            ],
                            "photo_reference": "CmRaAAAAfTgI_jWxWGzT6DmBDcs94bU-mSMu_gCh9-bcEVknMvEc3N3WRWcGqV3NUXIawYZ8ddwXyq7aatb92DC5jCkZF_bXZCVsAe7u2mK7zpbrR1DzQj-BczDhXpycxWGKb_1EEhBE-gqwGbobjZ62Tgfv-uG_GhRJlXGbLY7_3_a9qMmKE-O2-epecg",
                            "width": 1920
                        }
                    ],
                    "place_id": "ChIJUc1lFqoWrjsRxNlDQnIfgWs",
                    "rating": 3.2,
                    "reference": "CmRRAAAAdMQf9G55uYd9p80e_P85lUlUZnw1U6BjW_rWaNV-rOX6VC5DIOsRCO0MWwm2TGgaeDybrQfoV4a6UHRq33b54H99MIwnDYFkMYsJEOZcNQCS36anEKzcjDCCJtgHGzL_EhBqqkEVQfnB3B9CLCkRK3xOGhTyE60pLLQlVrvo-qVRwWA198wo9w",
                    "scope": "GOOGLE",
                    "types": [
                        "atm",
                        "bank",
                        "finance",
                        "point_of_interest",
                        "establishment"
                    ],
                    "vicinity": "No. 9, Eterna, Ganapathi Temple Road, 5th Block, Koramangala, Bengaluru"
                },
                {
                    "geometry": {
                        "location": {
                            "lat": 12.9357138,
                            "lng": 77.6169809
                        },
                        "viewport": {
                            "northeast": {
                                "lat": 12.9370875802915,
                                "lng": 77.6182029802915
                            },
                            "southwest": {
                                "lat": 12.9343896197085,
                                "lng": 77.6155050197085
                            }
                        }
                    },
                    "icon": "https://maps.gstatic.com/mapfiles/place_api/icons/atm-71.png",
                    "id": "44741afeefa36a7adf0e61bfc79facf64e49e509",
                    "name": "Punjab National Bank ATM",
                    "opening_hours": {
                        "open_now": true,
                        "weekday_text": []
                    },
                    "place_id": "ChIJGfxqyE8UrjsRfaIrGICnf74",
                    "rating": 4.3,
                    "reference": "CmRSAAAAv-tRma5WJIL9qrTwHAMkKQhEuT6oq9lGW9FgCvbaLYFKEF1K4DejdkH3NT9NGGD-aRmVl2RJDcGASmJkgXn6q6ClUJjcoo4Ukggux8mPmn4hloTsjLhdIZQ0JyacecuOEhBQ5LE_X82oLobdZossbUklGhS-PpqiMKrZbBjPzZm9Qey4YXl2Kw",
                    "scope": "GOOGLE",
                    "types": [
                        "atm",
                        "finance",
                        "point_of_interest",
                        "establishment"
                    ],
                    "vicinity": "112A, 17th Main Road, 5th Block, Koramangala, Bengaluru"
                },
                {
                    "geometry": {
                        "location": {
                            "lat": 12.9413056,
                            "lng": 77.61738489999999
                        },
                        "viewport": {
                            "northeast": {
                                "lat": 12.9426546302915,
                                "lng": 77.6187324302915
                            },
                            "southwest": {
                                "lat": 12.9399566697085,
                                "lng": 77.61603446970848
                            }
                        }
                    },
                    "icon": "https://maps.gstatic.com/mapfiles/place_api/icons/atm-71.png",
                    "id": "1e6346aa6974aee613bbd095bd5873fad9de3f25",
                    "name": "Karur Vysya Bank ATM",
                    "opening_hours": {
                        "open_now": true,
                        "weekday_text": []
                    },
                    "photos": [
                        {
                            "height": 2847,
                            "html_attributions": [
                                "<a href=\"https://maps.google.com/maps/contrib/107122305584469029330/photos\">Parashuram</a>"
                            ],
                            "photo_reference": "CmRaAAAA75SQWTyX2cJXeHIEky6kV0unM3K7ufRkwxqPoxF__OwxRuMFEcJCVYBn65YRk-6SP8JnS1sHdSW46mW5FJbIeubQrih6GWBgkfLTyJCZ3qWP7XKXxN-P1IhjQe7FBfs3EhBNi_xLYthjG52_DEnzX6UjGhSsLl1YopsQC0YajngNrxjuau62Qg",
                            "width": 2599
                        }
                    ],
                    "place_id": "ChIJ5_vzwUgUrjsRLsLfe0LaJrs",
                    "rating": 4,
                    "reference": "CmRSAAAAyEgL1wTFGg7HhqBRAYde3TUF7c8yC3rShmkgcpnR3Ma46lvAcA6GaA_V849-1MORob6XVCl3rrpmSzbGeJaJuAQlFJrFwZjjHGL-Oqzrk35qseKlYLEty2Tqo5wv6g7DEhBPRppDH2q4CladpZtimzltGhSsqkRq06Sc7wqCblLX2NsdWeORiA",
                    "scope": "GOOGLE",
                    "types": [
                        "atm",
                        "finance",
                        "point_of_interest",
                        "establishment"
                    ],
                    "vicinity": "38, S R Nest, 8th Block, Adugodi Main Road, Koramangala 8th Block, Koramangala, Bengaluru"
                },
                {
                    "geometry": {
                        "location": {
                            "lat": 12.9377498,
                            "lng": 77.6216269
                        },
                        "viewport": {
                            "northeast": {
                                "lat": 12.9390800302915,
                                "lng": 77.62295838029151
                            },
                            "southwest": {
                                "lat": 12.9363820697085,
                                "lng": 77.62026041970849
                            }
                        }
                    },
                    "icon": "https://maps.gstatic.com/mapfiles/place_api/icons/atm-71.png",
                    "id": "ec776724f59ea41c48a0d835d53f1619ccdb3860",
                    "name": "Oriental Bank of Commerce ATM",
                    "opening_hours": {
                        "open_now": true,
                        "weekday_text": []
                    },
                    "photos": [
                        {
                            "height": 4160,
                            "html_attributions": [
                                "<a href=\"https://maps.google.com/maps/contrib/112792955130206696242/photos\">parthipan rajgopal</a>"
                            ],
                            "photo_reference": "CmRaAAAALNjIQCJMPNTrBsHQaTOB6Qz5dtcCvUnMh3MbziZKfUPsOckinAPLFXUoXc7fjLkvIa1BX2rjMTi1rSmuojB14eLG9dAkmHkQO3b26M3yuGNuxNa71-rszuSU3QTwy2uQEhDATSOsNLQFRrdjgfnUg-o_GhTC0Gq_7WNgpqgw4u9MucETPunCOA",
                            "width": 2340
                        }
                    ],
                    "place_id": "ChIJx3MsqUUUrjsRXhg0iWmsV9g",
                    "rating": 2.8,
                    "reference": "CmRSAAAAKqqnKHjkzRWL7UhLpEusAAcT0VnEdKp8ROVApJCaHLAtGWVG9x9N7_LC6NY96Tsrpv7pKZ0q43eNmO5MQ1XC59mY3yTWoUqVUHkg-3pYbxhP1_rdFfBFUgILaKJ0BN8xEhBRHvK6QJBIFSYFmtZS_F4tGhTiUXPH8j-JvMYt1MSol2I-cQ7nTw",
                    "scope": "GOOGLE",
                    "types": [
                        "atm",
                        "finance",
                        "point_of_interest",
                        "establishment"
                    ],
                    "vicinity": "17th H Main Road, Indiranagar, 6th Block, Koramangala, Bengaluru"
                },
                {
                    "geometry": {
                        "location": {
                            "lat": 12.9365961,
                            "lng": 77.62056989999999
                        },
                        "viewport": {
                            "northeast": {
                                "lat": 12.9379450802915,
                                "lng": 77.6219188802915
                            },
                            "southwest": {
                                "lat": 12.9352471197085,
                                "lng": 77.6192209197085
                            }
                        }
                    },
                    "icon": "https://maps.gstatic.com/mapfiles/place_api/icons/bar-71.png",
                    "id": "4f0daee7fa77c6f7d29d7c82c00143b542bf6791",
                    "name": "Bundle Of Joy",
                    "opening_hours": {
                        "open_now": true,
                        "weekday_text": []
                    },
                    "photos": [
                        {
                            "height": 960,
                            "html_attributions": [
                                "<a href=\"https://maps.google.com/maps/contrib/116201397565954723903/photos\">Shameer Shameer</a>"
                            ],
                            "photo_reference": "CmRaAAAAfU1OCwtpa6L6iKJGCe7ywy1gpFXoQ571kxTB63vezKKVqL5RnozYYanXjcLhZTvw_RWbEjo-P-5DRiYq1tW9kB0iXq_hxY7QGnz_D7L8nB1TMyZzCle_pAQ5Ykt87MK-EhDhA8oZkx6ngKHWvwcSj-_UGhR0hE9XhOOkHLMCo923OHBRBXZL9A",
                            "width": 1280
                        }
                    ],
                    "place_id": "ChIJGXiBF0UUrjsR7qJRqepH60Q",
                    "rating": 4.1,
                    "reference": "CmRRAAAAtukn5AdbPfbTz_ZQ94QlgSKbMcYQalPnTS9gMlqHqKsr8glH2YXyzJZgGA952o6uqYBW5Wh6vtPBRxDILmG87Cx7psWWSAZ369DJB-ZM3J79J9HSO_sT1BR_5LSLYvaFEhBscUEpMl3WkZ-nu4S9HE9uGhTlgkCV-grww-dSatjSURugHJnY0Q",
                    "scope": "GOOGLE",
                    "types": [
                        "bar",
                        "atm",
                        "finance",
                        "clothing_store",
                        "store",
                        "restaurant",
                        "food",
                        "point_of_interest",
                        "establishment"
                    ],
                    "vicinity": "60 Feet Rd, 6 Block, Koramangala, Bengaluru"
                }
            ],
            "heat": 59.2,
            "lat": 12.94,
            "lng": 77.62
        },
        {
            "details": [
                {
                    "geometry": {
                        "location": {
                            "lat": 12.9371577,
                            "lng": 77.6273132
                        },
                        "viewport": {
                            "northeast": {
                                "lat": 12.9385066802915,
                                "lng": 77.6286621802915
                            },
                            "southwest": {
                                "lat": 12.9358087197085,
                                "lng": 77.6259642197085
                            }
                        }
                    },
                    "icon": "https://maps.gstatic.com/mapfiles/place_api/icons/school-71.png",
                    "id": "befd4aae25dfba37a75130cb119199b6eb2bb0a4",
                    "name": "T. A. Pai Management Institute",
                    "place_id": "ChIJ-7nuGmwUrjsR5dYrrrhJEfU",
                    "rating": 4.5,
                    "reference": "CmRSAAAASCBT1KO6hoezdAA5z_5HkLxaamhQx2lJGKIgDyK3bx7OT209ONGokO-zMu2eLzj9hmuKO1Y2jKggWQyy4VetroKG53kT3I-H89WCSwD-q7nVYaXxNGiNejoNp7RCs8kDEhCOaDgn_xk-aggzeTpnOTWZGhRWKsvLIr8Yqy9SczNvbnuFonLYoA",
                    "scope": "GOOGLE",
                    "types": [
                        "university",
                        "school",
                        "point_of_interest",
                        "establishment"
                    ],
                    "vicinity": "3, 100 Feet Road, Near-BDA Complex, Mahakavi Vemana Road, Koramangala 4 Block, Koramangala, Bangalore Urban, Bengaluru"
                },
                {
                    "geometry": {
                        "location": {
                            "lat": 12.9366284,
                            "lng": 77.6251483
                        },
                        "viewport": {
                            "northeast": {
                                "lat": 12.9379773802915,
                                "lng": 77.6264972802915
                            },
                            "southwest": {
                                "lat": 12.9352794197085,
                                "lng": 77.6237993197085
                            }
                        }
                    },
                    "icon": "https://maps.gstatic.com/mapfiles/place_api/icons/bank_dollar-71.png",
                    "id": "7731d87ad4853da480e968f51f86f4e23662754c",
                    "name": "Indian Bank",
                    "opening_hours": {
                        "open_now": true,
                        "weekday_text": []
                    },
                    "place_id": "ChIJ01WAaEMUrjsROKTQp658fH0",
                    "rating": 3,
                    "reference": "CmRRAAAAG10L1GUxWzATn7996G2uyg4gGwG-A3B-wB9AupXmX9A10Ht0r6oFo99GOMedrSS3j5djDAZYpFSWYWq71d7ovMIuBjivWXR2wfqRmSrHmaICUBc0wSZr6ghXczsWF7-PEhBIU-Z8LoOObkV5Slexeq0gGhRrlPvqU4qChMdu10dfUs9okuDssQ",
                    "scope": "GOOGLE",
                    "types": [
                        "bank",
                        "atm",
                        "finance",
                        "point_of_interest",
                        "establishment"
                    ],
                    "vicinity": "630, 100 Feet Road, Near-Mahindra Show Room, Koramangala 6th Block, Bengaluru"
                },
                {
                    "geometry": {
                        "location": {
                            "lat": 12.93993,
                            "lng": 77.625157
                        },
                        "viewport": {
                            "northeast": {
                                "lat": 12.9413207802915,
                                "lng": 77.6265612302915
                            },
                            "southwest": {
                                "lat": 12.9386228197085,
                                "lng": 77.6238632697085
                            }
                        }
                    },
                    "icon": "https://maps.gstatic.com/mapfiles/place_api/icons/atm-71.png",
                    "id": "82ae82aa3755bba56f5280c00ec77bf500136bea",
                    "name": "IndusInd Bank ATM",
                    "opening_hours": {
                        "open_now": true,
                        "weekday_text": []
                    },
                    "photos": [
                        {
                            "height": 1872,
                            "html_attributions": [
                                "<a href=\"https://maps.google.com/maps/contrib/116869091064335399414/photos\">BK Gajendra</a>"
                            ],
                            "photo_reference": "CmRaAAAAXFbTPgbJf1p6c70Bih3zVtgxFFHS0OBACNWx-PXHQNE5cPJz04czGireMwL9Nu-yeBpdqaXs8cxHSEoXpzwpCE6GSNcmUSlt7PHhabxmVHVy0owK9UGYDukaDV6HmdaAEhBlgMicNVWum5AEXcF4YG0-GhT3IhoscAK41cdgCBK-uEFVbHrGYw",
                            "width": 3328
                        }
                    ],
                    "place_id": "ChIJfQ8j_EMUrjsRe1wwV2tuI1Q",
                    "rating": 4,
                    "reference": "CmRRAAAAmgMkSQQF7uulzM0rFAHcHkWie9WpKrJVZpHrpIN73_9Dmd3aON9fFUlccbGVwgkSmkm4W_RXpyMW4BOWEp5tuoPlVpTR40dvWhyzP-4M_94sjDwbNnJ40Z9nxu6g6-XOEhBQQkDFXaCBLv6ihLrB-ZJ0GhTUiKObs4Xat9WDGJujApmX8hEPHA",
                    "scope": "GOOGLE",
                    "types": [
                        "atm",
                        "finance",
                        "point_of_interest",
                        "establishment"
                    ],
                    "vicinity": "6th Block, No.478, Chambers II, in front of Bus depot, 560095, 80 Feet Road, 6th Block, Koramangala, Bengaluru"
                }
            ],
            "heat": 18.5,
            "lat": 12.94,
            "lng": 77.63
        },
        {
            "details": [
                {
                    "geometry": {
                        "location": {
                            "lat": 12.9490812,
                            "lng": 77.6209241
                        },
                        "viewport": {
                            "northeast": {
                                "lat": 12.9505185802915,
                                "lng": 77.6219909802915
                            },
                            "southwest": {
                                "lat": 12.9478206197085,
                                "lng": 77.61929301970848
                            }
                        }
                    },
                    "icon": "https://maps.gstatic.com/mapfiles/place_api/icons/school-71.png",
                    "id": "fdb83aee4247ea4325d57db51ea3c8f3fefafc4b",
                    "name": "National Public School",
                    "photos": [
                        {
                            "height": 3024,
                            "html_attributions": [
                                "<a href=\"https://maps.google.com/maps/contrib/116064173152307485564/photos\">Samhitha Bharthulwar</a>"
                            ],
                            "photo_reference": "CmRaAAAARO07z02hWMZ3Buz3drkVRKLjLwMHV4QfxRCeW1eP0d5BzKZhGTT4eCoRwCQ9PNN9UUPaA6D3ICu1-WeVB86xHCB5g9iEMmqX0_BAgBirNZzociP5hVI4kyg8bdssnpljEhANhHO2rLXomBLdZTrWzAnaGhTD0X9FjaGMG90q7InT-7n9QVf3Rw",
                            "width": 4032
                        }
                    ],
                    "place_id": "ChIJgwbBtzkUrjsRUgILl8pxu-4",
                    "rating": 4,
                    "reference": "CmRSAAAA4uAFKc8AOincNRh7cag61rGkryPHc2zhuisrK10JLvzLYWXJvkeQMXelgc2w1rygB208JKgQSHDmLm4YkiD_itHhR771cNJQcEQh2ppc1dlj8aHH0WcQV3JOCAj-OvRcEhB6tfgrSHJcqY02kv3reShUGhQs9yjXT9FsHX2NLP9lDxNmFf4AoQ",
                    "scope": "GOOGLE",
                    "types": [
                        "school",
                        "point_of_interest",
                        "establishment"
                    ],
                    "vicinity": "National Games Village, 80 Feet Main Rd, Koramangala, Bengaluru"
                }
            ],
            "heat": 4,
            "lat": 12.95,
            "lng": 77.62
        },
        {
            "details": [
                {
                    "geometry": {
                        "location": {
                            "lat": 12.9263173,
                            "lng": 77.6249287
                        },
                        "viewport": {
                            "northeast": {
                                "lat": 12.9275691302915,
                                "lng": 77.62618933029151
                            },
                            "southwest": {
                                "lat": 12.9248711697085,
                                "lng": 77.6234913697085
                            }
                        }
                    },
                    "icon": "https://maps.gstatic.com/mapfiles/place_api/icons/school-71.png",
                    "id": "2a878ed6db29488113f7487b71d257139afdefd7",
                    "name": "Greenwood High Pre Schools",
                    "photos": [
                        {
                            "height": 1232,
                            "html_attributions": [
                                "<a href=\"https://maps.google.com/maps/contrib/106909334370788177794/photos\">Atma Ram</a>"
                            ],
                            "photo_reference": "CmRaAAAAHgdulO_LPWnnC4deCUweO7a72z8Sr4SNCOk27AZRzLGITFbjYewizogv34mycej--1FDylySvjo2zKOJfrZOwx7DHOrYoKec6R325HjTB_KMcS4yzI_cp4K9CrXSfoXlEhBcewj_vZp1OncCvC34G0tpGhR_ODfM0UffW2eqHtCWdoxOEZ8QVQ",
                            "width": 2048
                        }
                    ],
                    "place_id": "ChIJfUU9KlkUrjsR-wTxwkhzvK8",
                    "rating": 3.7,
                    "reference": "CmRSAAAAOht-bAEfxXsEXubzPcaI4zpKrtsito3qHEBPR3oDsP-y4JN_-1cZ4GhugiLLJEf_WjzP8cEV6o_v8sMVwKE1oLSC9Heot1j1LVPgQXRkxk1BHUCabneIsCtQXB9BkSj_EhA6jiGZgFBKe9a7DXkI1CXbGhTDl0p3L18V5WqhPEDgLRh2lgwHtA",
                    "scope": "GOOGLE",
                    "types": [
                        "school",
                        "point_of_interest",
                        "establishment"
                    ],
                    "vicinity": "377, Sarjapur Road, Koramangala 3rd Block, Bengaluru, 560034"
                },
                {
                    "geometry": {
                        "location": {
                            "lat": 12.928903,
                            "lng": 77.62168
                        },
                        "viewport": {
                            "northeast": {
                                "lat": 12.9302519802915,
                                "lng": 77.6230289802915
                            },
                            "southwest": {
                                "lat": 12.9275540197085,
                                "lng": 77.62033101970849
                            }
                        }
                    },
                    "icon": "https://maps.gstatic.com/mapfiles/place_api/icons/school-71.png",
                    "id": "d4a7bc88e3d2ac3187552b291e9b0f7d6d0f4620",
                    "name": "Child-Care Montessori",
                    "opening_hours": {
                        "open_now": true,
                        "weekday_text": []
                    },
                    "photos": [
                        {
                            "height": 1536,
                            "html_attributions": [
                                "<a href=\"https://maps.google.com/maps/contrib/105333910799442034756/photos\">Child-Care Montessori</a>"
                            ],
                            "photo_reference": "CmRaAAAA_m2aQsvKdert3rPFtyL8_4DaF8IiyB5-5CsjXj7JBJKi-DY0y7ekk7Ar3ptSANGa2pc8zqNNXBMytEXNgLjO1D9KoCNp98rfS_UqEuE--S39AJZQQNFbLJZHbb9nMrIuEhAFCSkgnR0Bo7qu_QjMITlzGhTsfesdLL5nKIEV2w473AyxzyMbnQ",
                            "width": 2048
                        }
                    ],
                    "place_id": "ChIJIWUcgVkUrjsRk8AOdrELt0E",
                    "rating": 4.5,
                    "reference": "CmRRAAAAG8Ei5kvm7Z8q-UHaXU9VNiuq5W-FCOpHF2nGwvoerKM7VmKhOw4W5X2TLdKe--mNZ-Ypc817H-yGDPlFIkt17l3QKQmg5Wdr8yAPCKnmYKWAJL1swMKDJCxYsfiOo7x0EhCGoFx5Dxu_pSGx4uTIDSxmGhTiSu1yJEPjCphM_v92faGK7wuPUw",
                    "scope": "GOOGLE",
                    "types": [
                        "school",
                        "point_of_interest",
                        "establishment"
                    ],
                    "vicinity": "# 632, 4th Cross, 100 Feet Road, 3rd Block, Koramangala,, Bengaluru"
                },
                {
                    "geometry": {
                        "location": {
                            "lat": 12.9308848,
                            "lng": 77.6207209
                        },
                        "viewport": {
                            "northeast": {
                                "lat": 12.93209595,
                                "lng": 77.62188359999999
                            },
                            "southwest": {
                                "lat": 12.92725135,
                                "lng": 77.61814079999999
                            }
                        }
                    },
                    "icon": "https://maps.gstatic.com/mapfiles/place_api/icons/school-71.png",
                    "id": "0840db6cbd51237b12e072f0216e765d8414cdcd",
                    "name": "St John s National Academy of Health Sciences",
                    "place_id": "ChIJieXePlEUrjsRzi81fy9BCa4",
                    "rating": 3.7,
                    "reference": "CmRSAAAA6L_jlWZ6ro3VfqFw8Gb5MlwIPRuI1jTD1QMop36S0NM2IenPKhno7CiyoVvQWRR_WgwzCvLUOFEBzfttu5nJ5YELi-m1WvRQXo5bQlzAyiR3lmeK8Pr5Oe3a6SU_UR9PEhDtizuK842ZATtNL6rxYYsbGhQ1yFtfHjx9XRfSCB_WzlhtNwdj8Q",
                    "scope": "GOOGLE",
                    "types": [
                        "university",
                        "school",
                        "point_of_interest",
                        "establishment"
                    ],
                    "vicinity": "Sarjapur Main Road, John Nagar, Koramangala, Bengaluru"
                },
                {
                    "geometry": {
                        "location": {
                            "lat": 12.9306752,
                            "lng": 77.6230326
                        },
                        "viewport": {
                            "northeast": {
                                "lat": 12.9320241802915,
                                "lng": 77.6243815802915
                            },
                            "southwest": {
                                "lat": 12.9293262197085,
                                "lng": 77.62168361970849
                            }
                        }
                    },
                    "icon": "https://maps.gstatic.com/mapfiles/place_api/icons/atm-71.png",
                    "id": "2d84459440e1d89971f25977276516306e980a44",
                    "name": "Syndicate Bank ATM",
                    "opening_hours": {
                        "open_now": true,
                        "weekday_text": []
                    },
                    "place_id": "ChIJw9ylvFsUrjsRjE16KlaOO9A",
                    "rating": 3.9,
                    "reference": "CmRSAAAAKsy6DwC0IYtZm8SqdJ19BC4dkaimk0D0q3sqXSmChH9-sGfzTQyZFsvKCQC_VZzvwX-bvGVE64rjpi6oCwxKAeYw35CECj84h6vAk4RDyofJrefB8qdT1zVYbgxDZhC8EhCxYPF56YDq0R14aK9Gw1LMGhQB3EVORd6-Vm11m7LWPLLE1ON-tw",
                    "scope": "GOOGLE",
                    "types": [
                        "atm",
                        "bank",
                        "finance",
                        "point_of_interest",
                        "establishment"
                    ],
                    "vicinity": "1st Floor, 965 & 966, Lig, 18rh `b` Cross, 2nd Phase, Yelahanka, Yelahanka, Bengaluru"
                },
                {
                    "geometry": {
                        "location": {
                            "lat": 12.926356,
                            "lng": 77.61683239999999
                        },
                        "viewport": {
                            "northeast": {
                                "lat": 12.9277049802915,
                                "lng": 77.61818138029149
                            },
                            "southwest": {
                                "lat": 12.9250070197085,
                                "lng": 77.61548341970848
                            }
                        }
                    },
                    "icon": "https://maps.gstatic.com/mapfiles/place_api/icons/atm-71.png",
                    "id": "9907243bf09520cd63c4a0fcb93746ddcf71be06",
                    "name": "Citibank ATM",
                    "opening_hours": {
                        "open_now": true,
                        "weekday_text": []
                    },
                    "photos": [
                        {
                            "height": 1536,
                            "html_attributions": [
                                "<a href=\"https://maps.google.com/maps/contrib/107336188543999441135/photos\">devanand subbaraj</a>"
                            ],
                            "photo_reference": "CmRaAAAAquHcYlBtUD9PdSDHCWThIMoVEIauWDe6BSMY08rHPr-9XnZUSKSNPhwgRDOBoHXtPiOVkomwy6jkffARYyZcnkIQIw-l2JqrC4LTJyyJOMZeccvU_wK4TctJh0mvLMTNEhChbtDv6w0khFtj5hcD8rLBGhQKz9DA1lHHZdL8MByAfBg_win68w",
                            "width": 2048
                        }
                    ],
                    "place_id": "ChIJ0bdGBFcUrjsRiCSWApZeZ48",
                    "rating": 3.5,
                    "reference": "CmRSAAAAImdw4VET8ZSlsZz_a-7rpuo9faTdBL_JD6uaR9CqBjNN7RWCtcS6Dq1uCCkwEEzlScsZs6sC9xW_1GAY85gdX6DSYessaJXT4MWCwjKZPvCWJxfcIYdZjJJK136I5oDHEhCmvqXUXqoMD7ggEtMqDrhdGhQN-i_XTcV_maMULOwR6Pn056bZ4g",
                    "scope": "GOOGLE",
                    "types": [
                        "atm",
                        "finance",
                        "point_of_interest",
                        "establishment"
                    ],
                    "vicinity": "No. 78/5, SMS Building, NH 7, Koramangala 2 Block, 1st Stage, Koramangala, Bengaluru"
                },
                {
                    "geometry": {
                        "location": {
                            "lat": 12.932125,
                            "lng": 77.622978
                        },
                        "viewport": {
                            "northeast": {
                                "lat": 12.9334739802915,
                                "lng": 77.6243269802915
                            },
                            "southwest": {
                                "lat": 12.9307760197085,
                                "lng": 77.6216290197085
                            }
                        }
                    },
                    "icon": "https://maps.gstatic.com/mapfiles/place_api/icons/atm-71.png",
                    "id": "1b6da59712d43d139bb8d1d8d2483cebd57ad37a",
                    "name": "ICICI Bank ATM",
                    "opening_hours": {
                        "open_now": true,
                        "weekday_text": []
                    },
                    "place_id": "ChIJ71ZuD1sUrjsRj2PbG1snn3c",
                    "reference": "CmRRAAAAUA8DgyCzBR6gxLkPcAY2wn1lnKjiR4fz7REmHOzc38073hWRGEVqm8_-kAujhoxtG9Uf4f8vwntnHTellpuO36g-abHxBVktSXSeyXKG0o5hcXjUEEj0d6UVZdjCx1uLEhBjRAprKec6VL_-TCg4ak_wGhTzJ7kaE7t0nCHOxu5MDhd0SEfo1g",
                    "scope": "GOOGLE",
                    "types": [
                        "atm",
                        "finance",
                        "point_of_interest",
                        "establishment"
                    ],
                    "vicinity": "KHB Block Koramangala, Koramangala 4-B Block, Koramangala, Bengaluru"
                },
                {
                    "geometry": {
                        "location": {
                            "lat": 12.9254729,
                            "lng": 77.6171039
                        },
                        "viewport": {
                            "northeast": {
                                "lat": 12.9268218802915,
                                "lng": 77.61845288029151
                            },
                            "southwest": {
                                "lat": 12.9241239197085,
                                "lng": 77.61575491970851
                            }
                        }
                    },
                    "icon": "https://maps.gstatic.com/mapfiles/place_api/icons/atm-71.png",
                    "id": "2629137afcc92d94d634c620c289c39b6741a236",
                    "name": "Canara Bank ATM",
                    "opening_hours": {
                        "open_now": true,
                        "weekday_text": []
                    },
                    "place_id": "ChIJ--F1APgUrjsRE1cGHRapdCY",
                    "rating": 3.3,
                    "reference": "CmRRAAAAHhDCLQmEgai8KGcUE_mYMSvNc5sYXnRy-A8foq8fXb0HHAqoFlv_gXlfHHxsRL6pYSDfol7NLiMIwjchb4Sjl9UkRLy16BHb84EVhF1Xc_UZoKGryntLXN3fM65LA1rAEhAjW_H5NxIXXtyUBaDWLmjmGhRSehFvACL2GUb2Tycb9Z5X2kVBEQ",
                    "scope": "GOOGLE",
                    "types": [
                        "atm",
                        "bank",
                        "finance",
                        "point_of_interest",
                        "establishment"
                    ],
                    "vicinity": "Zuzuvadi, HSR layout Sector 2, 1st Stage, Suddagunte Palya, Bengaluru"
                },
                {
                    "geometry": {
                        "location": {
                            "lat": 12.9316556,
                            "lng": 77.6226959
                        },
                        "viewport": {
                            "northeast": {
                                "lat": 12.9330045802915,
                                "lng": 77.6240448802915
                            },
                            "southwest": {
                                "lat": 12.9303066197085,
                                "lng": 77.62134691970849
                            }
                        }
                    },
                    "icon": "https://maps.gstatic.com/mapfiles/place_api/icons/atm-71.png",
                    "id": "166e64ad12918e72c5e63050c1e1610548a3ad46",
                    "name": "UCO Bank",
                    "opening_hours": {
                        "open_now": true,
                        "weekday_text": []
                    },
                    "photos": [
                        {
                            "height": 357,
                            "html_attributions": [
                                "<a href=\"https://maps.google.com/maps/contrib/115274573399948558690/photos\">Foshes Technologies</a>"
                            ],
                            "photo_reference": "CmRaAAAAB0UC3ukANOYFEbcMH20ZAt9qIt4RgcKHZxirfWNivPDfz8X0JYn1ynYDecHDFm6uvMS_X7I_ZhZxuy-BMwQmxibDDrW32V0b2holDKhKVOLC2dM9QQXVRSE2JOJ3N0r8EhAJ4-KUeYOQlLXyAlqrCL6sGhS2LYq3jnxeyMWOvy-BitjT56H-8g",
                            "width": 357
                        }
                    ],
                    "place_id": "ChIJK8BZqFsUrjsRbn57ZfoQs6g",
                    "rating": 2.3,
                    "reference": "CmRSAAAAvaRsAYjDUQ3rTvfe4Y1mIC6ivuglAW8E1YK6bbrqjpW-kG9fbcLIY5Wv-giSj_vVhDLJDTOpfDX8AC45T-tKM8gcHRCH-37PsAb5PoQGmq8g7YwRqbUcHd0JKTuoaLLjEhC2F31RIPvOPyVla9PX9ZSoGhTQ-YfQSzHkTE4i_KV8AgNyJ97erQ",
                    "scope": "GOOGLE",
                    "types": [
                        "atm",
                        "finance",
                        "point_of_interest",
                        "establishment"
                    ],
                    "vicinity": "India"
                },
                {
                    "geometry": {
                        "location": {
                            "lat": 12.9335532,
                            "lng": 77.62326569999999
                        },
                        "viewport": {
                            "northeast": {
                                "lat": 12.9348969302915,
                                "lng": 77.6246258802915
                            },
                            "southwest": {
                                "lat": 12.9321989697085,
                                "lng": 77.6219279197085
                            }
                        }
                    },
                    "icon": "https://maps.gstatic.com/mapfiles/place_api/icons/atm-71.png",
                    "id": "23ca4206ed8d30061b89c1079cfa9c324a78c3bb",
                    "name": "Kotak Mahindra Bank ATM",
                    "opening_hours": {
                        "open_now": true,
                        "weekday_text": []
                    },
                    "place_id": "ChIJDfOxPlsUrjsRWkw80Bnze2I",
                    "reference": "CmRRAAAAwhNnDGNYuMmZp4dtKfEGEqPy3mcJFAj-sYDpSRrMcJTlB8746nxrh5_EunkTyme9HVjkruDGL1sejLxDGslwrZRGFFKTW8xMt-ZC9HqNH2Pwyyhtd7dCOUJvOknHMrKbEhCe1Wc8x6DOGpqDTPvtXuKNGhS6Cx0ftY6jNx1GZpqcsEFuXcEwlg",
                    "scope": "GOOGLE",
                    "types": [
                        "atm",
                        "finance",
                        "point_of_interest",
                        "establishment"
                    ],
                    "vicinity": "A Cross Road, 100 Feet Road, Koramangala, Bengaluru"
                }
            ],
            "heat": 47.9,
            "lat": 12.93,
            "lng": 77.62
        },
        {
            "details": [
                {
                    "geometry": {
                        "location": {
                            "lat": 12.9300602,
                            "lng": 77.6314586
                        },
                        "viewport": {
                            "northeast": {
                                "lat": 12.9314091802915,
                                "lng": 77.63280758029151
                            },
                            "southwest": {
                                "lat": 12.9287112197085,
                                "lng": 77.6301096197085
                            }
                        }
                    },
                    "icon": "https://maps.gstatic.com/mapfiles/place_api/icons/school-71.png",
                    "id": "36d248a4b3ea32f12d7354428af81ed8c2c60a51",
                    "name": "Bangalore Public School",
                    "place_id": "ChIJVVVVhQIUrjsRMZpf3yda_kk",
                    "rating": 4.1,
                    "reference": "CmRRAAAAbDKKepj-FQDa6SSNhvwuhbUA6A_YR97hzjYFqMBEzZtJfq6EtcnpslGXz9VNLhBUqGlDMr13GiJfqubcgP6ChQzu387uo03eQJskITNYqXj0jkUir699bNs64GV0L-KnEhBo870GqqLvwd1738VKLuaxGhQQlEdmNAHP7DcACuZcDdvYkL6taQ",
                    "scope": "GOOGLE",
                    "types": [
                        "school",
                        "point_of_interest",
                        "establishment"
                    ],
                    "vicinity": "India"
                },
                {
                    "geometry": {
                        "location": {
                            "lat": 12.9252766,
                            "lng": 77.6290851
                        },
                        "viewport": {
                            "northeast": {
                                "lat": 12.9261616302915,
                                "lng": 77.63079183029151
                            },
                            "southwest": {
                                "lat": 12.9234636697085,
                                "lng": 77.62809386970851
                            }
                        }
                    },
                    "icon": "https://maps.gstatic.com/mapfiles/place_api/icons/school-71.png",
                    "id": "897b375ba38682abadec07b0e8bee9c9e6ee98fa",
                    "name": "St. Francis High School",
                    "photos": [
                        {
                            "height": 1365,
                            "html_attributions": [
                                "<a href=\"https://maps.google.com/maps/contrib/105173688066587128571/photos\">St. Francis High School</a>"
                            ],
                            "photo_reference": "CmRaAAAAYwnCexdYLGyK4tHE5yVBNLXwu-sO_aWPTGv2u-DDjpV7WKVU25Jvhz6j_B3G6eURGwIgz2Wz2gzz3bbpcf5wViq9mMm40wpaucLKl4eqsh50agrFaJSzhLBP646GaPgaEhD9CV40CfthIBiKElz30s7oGhRunpmQHzhOaBAo8LuUpUhJG8DoAw",
                            "width": 2048
                        }
                    ],
                    "place_id": "ChIJWbZr3l0UrjsRUROw16fm4sY",
                    "rating": 4.4,
                    "reference": "CmRSAAAAfNSUIDLAVJyvDDHFty5NSXXxtcIQtOa-xkcCLg7VBJWZ4wDo9GmVL7caOtGaMxVe21lW_N_Reh1Dnzds6hsL3me1PEH4coHrnwNTwRjVeYiLm6EDdlo3b0Fwny9E0m4_EhCKbY3oxV10K0TtcMSokGkKGhQPtGyABDBjA8oXwYMxwh9mJB1bYQ",
                    "scope": "GOOGLE",
                    "types": [
                        "school",
                        "point_of_interest",
                        "establishment"
                    ],
                    "vicinity": "Sarjapur Main Road, Koramangala 3 Block, Opp. to Krupa Nidhi College, Bengaluru"
                },
                {
                    "geometry": {
                        "location": {
                            "lat": 12.9349957,
                            "lng": 77.6276958
                        },
                        "viewport": {
                            "northeast": {
                                "lat": 12.9362272802915,
                                "lng": 77.6291407302915
                            },
                            "southwest": {
                                "lat": 12.9335293197085,
                                "lng": 77.62644276970849
                            }
                        }
                    },
                    "icon": "https://maps.gstatic.com/mapfiles/place_api/icons/school-71.png",
                    "id": "563807507e7325c050bef9cdad661eb3c492eb4b",
                    "name": "Chinmaya Vidyalaya",
                    "photos": [
                        {
                            "height": 3456,
                            "html_attributions": [
                                "<a href=\"https://maps.google.com/maps/contrib/110654645567144636966/photos\">Bob nair</a>"
                            ],
                            "photo_reference": "CmRaAAAAzTyYAyiX744Xi2c0mTvnj5eJ1mdEONKPXuW4-BIFlJnQCpcpK5B7UYgh_hJ2WCckEvb7w8VOy20pHL53G8GX7f3wqDHH39MhIOdiuXZStH7PdMUbQX-Nxt7rEpPvMzovEhDkR_mcwwggyxLUoACfO_uXGhRaXUjCRsvaz8scJH2W43ix1_rRcQ",
                            "width": 4608
                        }
                    ],
                    "place_id": "ChIJp0gH1FwUrjsRRkPHA7Hpsnw",
                    "rating": 4.3,
                    "reference": "CmRRAAAALncFL-zFtaRZo1j5nm-idazr2IUWXr1elFg6Gw_IETEHjNktATh9P7o0-NVlG7NP_3-ieOumQXrtmdaNkymNCkz9LqZmefJzC5gyhNg4fROc3Q5Rafzlg_EZwxoJlsl1EhCZXvlWkAKlEDQVd--0f1RYGhQ8bS5IB_VbNnd3LR4CY8o4b4VxVw",
                    "scope": "GOOGLE",
                    "types": [
                        "school",
                        "point_of_interest",
                        "establishment"
                    ],
                    "vicinity": "India"
                },
                {
                    "geometry": {
                        "location": {
                            "lat": 12.9335947,
                            "lng": 77.6271874
                        },
                        "viewport": {
                            "northeast": {
                                "lat": 12.9349436802915,
                                "lng": 77.6285363802915
                            },
                            "southwest": {
                                "lat": 12.9322457197085,
                                "lng": 77.62583841970849
                            }
                        }
                    },
                    "icon": "https://maps.gstatic.com/mapfiles/place_api/icons/school-71.png",
                    "id": "ff694f8e0cf51a80abb4c9c3060507b263dfd438",
                    "name": "Little Paradise",
                    "opening_hours": {
                        "open_now": true,
                        "weekday_text": []
                    },
                    "photos": [
                        {
                            "height": 720,
                            "html_attributions": [
                                "<a href=\"https://maps.google.com/maps/contrib/113607854185569593653/photos\">Tuli Biswas</a>"
                            ],
                            "photo_reference": "CmRaAAAASNsvhwb69rd_jaVqnMpz2qqcZV6rclYxRQuWR921LbVBmTn2CUvSzbQqm7syM6bfxujoIJmYer03m9Cp7m1tiyyaB4D6clLYYiwmpmfmP85a6H_CohvoP8Z7rR8BgF0REhDgpVt9-9hiRJ6xuMxqq6RMGhQhge9KE44f8ey_xPveJCiX_4DL8w",
                            "width": 960
                        }
                    ],
                    "place_id": "ChIJZS_T3FwUrjsRXOra6z7557A",
                    "reference": "CmRSAAAA6y9qxpiVTARJOyzFNoiTri1xUaSSON99b_JxlzQgJXQg4rh-IUUPyY_Pf7TrQmDFv2FlW_soHmhXTkduZNuJnjzqLH58ONBW0rjD2QU3lBDQSal_CoUZenQcCj4TijNBEhD72Oq2PFekszh-HRbKXx0GGhQm5gJA0zOnBossuwvs0PbDqJQBYw",
                    "scope": "GOOGLE",
                    "types": [
                        "school",
                        "point_of_interest",
                        "establishment"
                    ],
                    "vicinity": "561, 8 Main, Koramangala 4 Block, Koramangala, Bengaluru"
                },
                {
                    "geometry": {
                        "location": {
                            "lat": 12.927824,
                            "lng": 77.628479
                        },
                        "viewport": {
                            "northeast": {
                                "lat": 12.9291729802915,
                                "lng": 77.62982798029151
                            },
                            "southwest": {
                                "lat": 12.9264750197085,
                                "lng": 77.62713001970849
                            }
                        }
                    },
                    "icon": "https://maps.gstatic.com/mapfiles/place_api/icons/school-71.png",
                    "id": "3118218934354476e2165991941b02e3fdf92885",
                    "name": "Pitter Patter Preschool",
                    "opening_hours": {
                        "open_now": false,
                        "weekday_text": []
                    },
                    "photos": [
                        {
                            "height": 1023,
                            "html_attributions": [
                                "<a href=\"https://maps.google.com/maps/contrib/104509228861145361907/photos\">Pitter Patter Preschool</a>"
                            ],
                            "photo_reference": "CmRaAAAAkXWCcAPHSM5mJX9xyK1meBpmV4idFKK_r9ywJYf64jg8NJRVWwHVUs5t6IHm8GXtcuc1CiHsikCgXqU3bPkABDMrLwsr4BECAo8Yyo-0PieEBKdLuXlLoZM0KdZ4XBzqEhCEGx-bNGR6NJzJHme7uxN3GhQpryc-KjS5u4pBZPml0EFzKM6osQ",
                            "width": 1319
                        }
                    ],
                    "place_id": "ChIJIXCfWl4UrjsRGZbMtioKI00",
                    "rating": 4,
                    "reference": "CmRRAAAAJRMLwNGxT8ArKLcy6YB3b2ngGP9i0uj4oka1m-bjNhvhRD0XGQ_aw9qlWUxLFVHObXTqnumNaLr9n_Hb94BzIhrrV6jfKK_-ElUh3oT8OlmI1ZBF2GONeuozhvEN5mBWEhAF6c66uyd0pBVXPN3oZmSiGhSVXclKsDGKXViljvsixwmuyNYmsQ",
                    "scope": "GOOGLE",
                    "types": [
                        "school",
                        "point_of_interest",
                        "establishment"
                    ],
                    "vicinity": "No 774, 9th Main, 3rd Block, Koramangala, Bengaluru"
                },
                {
                    "geometry": {
                        "location": {
                            "lat": 12.9299204,
                            "lng": 77.63335620000001
                        },
                        "viewport": {
                            "northeast": {
                                "lat": 12.9312499802915,
                                "lng": 77.6347043302915
                            },
                            "southwest": {
                                "lat": 12.9285520197085,
                                "lng": 77.63200636970849
                            }
                        }
                    },
                    "icon": "https://maps.gstatic.com/mapfiles/place_api/icons/school-71.png",
                    "id": "708a72e60666a84933aebac40c14e888a6ef4dcf",
                    "name": "Moms And Tots",
                    "place_id": "ChIJHdhzKWcUrjsRJdg5p7TSxBw",
                    "reference": "CmRRAAAAbmk6MaO3kEIgQmLjBItXSbZmkR3-MIzt7ZjNOJBcR6c-5lmfcLt6ff8kwA3Qctpu0b7T8uUDFn82ihF9B42uoyVeST438fJqJH2beRdpYVwnlO3EnL2CtuTXVry0Re_mEhAyKyUfvzOoKYYea0TWqT40GhQy8N8_eqK4s-I_T3ewjXYA2KWJvw",
                    "scope": "GOOGLE",
                    "types": [
                        "school",
                        "point_of_interest",
                        "establishment"
                    ],
                    "vicinity": "1000, 1st Main Road, S.T. Bed, 1st Block Koramangala, Koramangala, Bengaluru"
                },
                {
                    "geometry": {
                        "location": {
                            "lat": 12.9300564,
                            "lng": 77.62943949999999
                        },
                        "viewport": {
                            "northeast": {
                                "lat": 12.9313799802915,
                                "lng": 77.6306950802915
                            },
                            "southwest": {
                                "lat": 12.9286820197085,
                                "lng": 77.6279971197085
                            }
                        }
                    },
                    "icon": "https://maps.gstatic.com/mapfiles/place_api/icons/school-71.png",
                    "id": "4ef9b092409891af2a894b09a05e758c1e6b9d20",
                    "name": "Maplebear - Koramangala",
                    "opening_hours": {
                        "open_now": true,
                        "weekday_text": []
                    },
                    "photos": [
                        {
                            "height": 3264,
                            "html_attributions": [
                                "<a href=\"https://maps.google.com/maps/contrib/113659479928070054304/photos\">viewme pro</a>"
                            ],
                            "photo_reference": "CmRaAAAAZFljin0cSvP4F-I9E3WUFgNqbKIBWHhc9aUD5BGtxbSgNLP91TFoWl7STKmqdRSnu8sBn-OngQMxyt10rXtcKVP__ET_wlj94pc5S7Wg9fURf9tG5J8hQSWF3POivRLrEhCMRN_NZA_vFOgoFyQnCgYgGhT_29_Glw9PQDQGxBbkHpa_rYP-bw",
                            "width": 4928
                        }
                    ],
                    "place_id": "ChIJ2____1oUrjsRCGqCOEEOO20",
                    "rating": 5,
                    "reference": "CmRRAAAAnQJFDw-qrK8GCvrMWvfkDXutXAauL83edF7TqF14T8iBdne2QsyGwAGrfxuoZm_MwjKmuYiCEIOVatFs2tBUD-iwgyIF5VQm1XfErFIyOr8R87kqistTfxCQ7HsMKiDeEhBWiP1HVLko6HIpWmUqEcbyGhQc4w_J76FFG1uUiZwc_71atffA1Q",
                    "scope": "GOOGLE",
                    "types": [
                        "school",
                        "point_of_interest",
                        "establishment"
                    ],
                    "vicinity": "531, 8th Main Road, 7th Cross, Koramangala 4th Block, Koramangala, Bengaluru"
                },
                {
                    "geometry": {
                        "location": {
                            "lat": 12.931203,
                            "lng": 77.629352
                        },
                        "viewport": {
                            "northeast": {
                                "lat": 12.9325519802915,
                                "lng": 77.63070098029151
                            },
                            "southwest": {
                                "lat": 12.9298540197085,
                                "lng": 77.6280030197085
                            }
                        }
                    },
                    "icon": "https://maps.gstatic.com/mapfiles/place_api/icons/school-71.png",
                    "id": "e1333c587e769734cb10d8ce43a52fa638da11e6",
                    "name": "I play I Learn- Indira Nagar",
                    "place_id": "ChIJKZBqyqUWrjsRQjsP0OyMsRw",
                    "reference": "CmRRAAAAPN4a1vEpYwKuxb5r-q-8924wgw7AOcv-jzxMSKp_EufRizPaSN6QuF7ETblgOtyJs99ZIohEcMzP3jkz7p0c5ILYypeEOMimVWbji3j3Zl2DFo8ZqDO7mOLPT1Ro9KMnEhDTtv-q7uj0Pdpi685FyVw3GhSwWREDW_Kj_kKzLUmUNYvBk_oBLA",
                    "scope": "GOOGLE",
                    "types": [
                        "school",
                        "point_of_interest",
                        "establishment"
                    ],
                    "vicinity": "House No. No. 31, 10th Main 2nd Cross Indira Nagar, Bengaluru"
                }
            ],
            "heat": 29.3,
            "lat": 12.93,
            "lng": 77.63
        },
        {
            "details": [
                {
                    "geometry": {
                        "location": {
                            "lat": 12.9328382,
                            "lng": 77.6145572
                        },
                        "viewport": {
                            "northeast": {
                                "lat": 12.9341871802915,
                                "lng": 77.6159061802915
                            },
                            "southwest": {
                                "lat": 12.9314892197085,
                                "lng": 77.61320821970848
                            }
                        }
                    },
                    "icon": "https://maps.gstatic.com/mapfiles/place_api/icons/bank_dollar-71.png",
                    "id": "36948be499f999af785098ea43a40368787d6065",
                    "name": "State Bank of India - Koramangla Branch",
                    "opening_hours": {
                        "open_now": true,
                        "weekday_text": []
                    },
                    "photos": [
                        {
                            "height": 1536,
                            "html_attributions": [
                                "<a href=\"https://maps.google.com/maps/contrib/107336188543999441135/photos\">devanand subbaraj</a>"
                            ],
                            "photo_reference": "CmRaAAAA0WQtUA8RIE-UoTA_YW8hSXTNX-QugWAC0Er0YiPtEz--TEK2tLTAdS5XqAVK3OqQOQueDWGbw26PyDwA9f2rQ9z1SlFdh0Gd9YLTZDleVRT9726zxlq5PUhwIBi5KZDZEhCQNwMh1W_n_Ce537LeU4dmGhQFcGCuDkMv-wFPgCbES95yTqsMAw",
                            "width": 2048
                        }
                    ],
                    "place_id": "ChIJSwAATFAUrjsRYndcU2gdgSc",
                    "rating": 3.4,
                    "reference": "CmRRAAAAm_70Lxwi91JkUrdDfFV8bd_29AU22X07yKhCz8MSUUQNVB8iLJig9yaakbVdz5bwi4tBOBUfqMyj-riZK2jBE0SWkRdTrx2GYuBEjX1Ss9EGDbMDczd0i5FJjazTYKAKEhBpIKHXbh5oQqvuNaXa7sGIGhRtOJaM-EDgzwCeDPKO8LRzluYTPg",
                    "scope": "GOOGLE",
                    "types": [
                        "atm",
                        "bank",
                        "finance",
                        "point_of_interest",
                        "establishment"
                    ],
                    "vicinity": "No. 92, Ground Floor, ZED Square, Jyoti Nivas College Road, 5th Block, Koramangala, Bengaluru"
                },
                {
                    "geometry": {
                        "location": {
                            "lat": 12.9320036,
                            "lng": 77.6100491
                        },
                        "viewport": {
                            "northeast": {
                                "lat": 12.9333526802915,
                                "lng": 77.6113952802915
                            },
                            "southwest": {
                                "lat": 12.9306547197085,
                                "lng": 77.60869731970848
                            }
                        }
                    },
                    "icon": "https://maps.gstatic.com/mapfiles/place_api/icons/atm-71.png",
                    "id": "2a9f3acb90ba51fdce3038c5d80ca4386b43ac83",
                    "name": "Axis Bank ATM",
                    "opening_hours": {
                        "open_now": true,
                        "weekday_text": []
                    },
                    "photos": [
                        {
                            "height": 3120,
                            "html_attributions": [
                                "<a href=\"https://maps.google.com/maps/contrib/105975288042284079748/photos\">sebastian Joseph Kannothu</a>"
                            ],
                            "photo_reference": "CmRaAAAAuTIpm3g8EBLTz18tKjhw1iyMeAD6DCr5wC-cVzdBxFHxWFTCFlngO79VftvgJq3Zjh6y1KbYd4wGP8RMNGL1Y6J8ICpb2RT3ZGCMv_wd5fJodeOMiHM_EKb6tUrUMel8EhBFnmIiPD3yG0KlHwvOFl9AGhRWR0MCSwxvZ2u9iaAlL7cRvLGEMw",
                            "width": 4160
                        }
                    ],
                    "place_id": "ChIJfQl7_v0UrjsRZUQ6lfjpA_U",
                    "rating": 2.7,
                    "reference": "CmRSAAAAzkzZ9GSMwBIcCHyyNmuC0eWE2tj2w1kg8TseCsie25NE1w7_xJkl49C8LA2yLEChDGi26HRR9JXSzKfZmGTSonBJpG2-okkrrmATV8vGUivNuQFN-XizD1RCUeoQ1U4WEhAk3PIixj3SzBXDXhqeWZLzGhSz1tg_V5H3nwNn_Nf8msoj41wxlg",
                    "scope": "GOOGLE",
                    "types": [
                        "atm",
                        "finance",
                        "point_of_interest",
                        "establishment"
                    ],
                    "vicinity": "55-3, Tavarekere Main Road, Venkateshwara Layout, Suddagunte Palya, Bengaluru"
                }
            ],
            "heat": 12.2,
            "lat": 12.93,
            "lng": 77.61
        },
        {
            "details": [
                {
                    "geometry": {
                        "location": {
                            "lat": 12.9255378,
                            "lng": 77.63641989999999
                        },
                        "viewport": {
                            "northeast": {
                                "lat": 12.9268867802915,
                                "lng": 77.6377688802915
                            },
                            "southwest": {
                                "lat": 12.9241888197085,
                                "lng": 77.6350709197085
                            }
                        }
                    },
                    "icon": "https://maps.gstatic.com/mapfiles/place_api/icons/bank_dollar-71.png",
                    "id": "f74438b871fcb1a8ed37f85fa5a6700fe675ee13",
                    "name": "State Bank of India",
                    "photos": [
                        {
                            "height": 2448,
                            "html_attributions": [
                                "<a href=\"https://maps.google.com/maps/contrib/112328841848873755731/photos\">Shreyas C M</a>"
                            ],
                            "photo_reference": "CmRaAAAAjBAL-Se0vjKPHl2WLoweyPIgijTlUu55MmWn2kifkRFD03vvISq7-Dg6BmVw1lPNbW-s_kh2d6J783Acr8fu6c3F6yPa1uzuCDKB3K4D77sNVdokZaUSpSPKmmSTEsKREhBthTGrx_Uje_k4eRwP794pGhQwzcVuy8GIGfzrGU5HbStXIBH-lw",
                            "width": 3264
                        }
                    ],
                    "place_id": "ChIJPTNRHLkVrjsRoI5qP--meDY",
                    "rating": 3.2,
                    "reference": "CmRRAAAApnBKqVRLHOhHYpBmJ5SgGTCbC0CG7Yzct4FWfIc_QHDT4a4fPm06aJGz4k5eOMjhyQNwUFA4QucjTQdswEaOOqdVMdNUdcobEhdZ8UVX5b04UlioemEwkCHutrFefQP5EhCgzPvmduLIoc2Ui0XV8MRAGhQs8WGvYYhAC7B3CHyO-WRidHZQMA",
                    "scope": "GOOGLE",
                    "types": [
                        "bank",
                        "atm",
                        "finance",
                        "point_of_interest",
                        "establishment"
                    ],
                    "vicinity": "80 Feet Road , 2nd Cross, Bengaluru"
                }
            ],
            "heat": 6.4,
            "lat": 12.93,
            "lng": 77.64
        },
        {
            "details": [
                {
                    "geometry": {
                        "location": {
                            "lat": 12.918609,
                            "lng": 77.610356
                        },
                        "viewport": {
                            "northeast": {
                                "lat": 12.9199579802915,
                                "lng": 77.6117049802915
                            },
                            "southwest": {
                                "lat": 12.9172600197085,
                                "lng": 77.6090070197085
                            }
                        }
                    },
                    "icon": "https://maps.gstatic.com/mapfiles/place_api/icons/school-71.png",
                    "id": "83ddcadc87a53eb5b0d94093e8720d428103e03e",
                    "name": "Kidzee",
                    "opening_hours": {
                        "open_now": true,
                        "weekday_text": []
                    },
                    "photos": [
                        {
                            "height": 2109,
                            "html_attributions": [
                                "<a href=\"https://maps.google.com/maps/contrib/105975288042284079748/photos\">sebastian Joseph Kannothu</a>"
                            ],
                            "photo_reference": "CmRaAAAAV5BFppZcLqTQlHEs3rIWl34l1LkfL8YECFURDXUQcoj5mXhCExoZhLjqXGhBUi5XhSURfR0HQcCieMMOHg8Ka5gsAWgEQhi4k-estHH5RF5-E15bVulbLo3csx7VXRMiEhAvT86t86W98gxAUh7baj8aGhQ9a8DSYzvNrb1vieb-n2K_zP3ThA",
                            "width": 3707
                        }
                    ],
                    "place_id": "ChIJJbE9jfcUrjsRC3tiwcHXir8",
                    "rating": 3.2,
                    "reference": "CmRSAAAAqke0FZJwoii63yHp-A9692FCfreDp1lkogiiaPb_rgj3GqNi1WvCh4fvTSJ-Del5E20AfeiD1c5uXFjDYiDeg2KcIhrkGEkau3ybgwXI8hpk7oge39pUG-dsk55v3htYEhDbuEayz5xfWcxEIQqEyTC_GhRfCWcOB49uXp484dnUY-7PoCUX8Q",
                    "scope": "GOOGLE",
                    "types": [
                        "school",
                        "point_of_interest",
                        "establishment"
                    ],
                    "vicinity": "1023, 16th Main, 1st Stage, 1st Phase, Near Advaitha Petrol Bunk, Tavarekere Main Road, BTM Layout, Bengaluru"
                },
                {
                    "geometry": {
                        "location": {
                            "lat": 12.9176295,
                            "lng": 77.614403
                        },
                        "viewport": {
                            "northeast": {
                                "lat": 12.9189784802915,
                                "lng": 77.6157519802915
                            },
                            "southwest": {
                                "lat": 12.9162805197085,
                                "lng": 77.6130540197085
                            }
                        }
                    },
                    "icon": "https://maps.gstatic.com/mapfiles/place_api/icons/school-71.png",
                    "id": "c01dbc4bc007fb0d550f82c48a7051dbf6b4c29a",
                    "name": "IQRA International School",
                    "photos": [
                        {
                            "height": 912,
                            "html_attributions": [
                                "<a href=\"https://maps.google.com/maps/contrib/100950652584172670805/photos\">Syed Shahul</a>"
                            ],
                            "photo_reference": "CmRaAAAAj2NRmOIbLAkqwGEMa37AmPUm39sFe9Jp4Td7IrI9I3Cl66vkavi42sKosy3sJf3p4WYrLMXqvcvIG1AHwP64pHWNopQ5R9iQvU0cVmn7CgS_NYV4BA3FXnHq_Q9FvA7lEhBiC85b2lC6hS5pvMjF29vPGhQ_tobVbqhNLU_g6NyuZ_hC9CUeZg",
                            "width": 1368
                        }
                    ],
                    "place_id": "ChIJy44fa_cUrjsRMMcLFn2n3w0",
                    "rating": 4.6,
                    "reference": "CmRRAAAAG8W_3zE3sHbfv_U97aR_iRsvuZvOu6pyQvSTG2a9WHXCjMQI2TjzbxI8ZTd7z78aGatsJU5yx6IOUcTSjbBrIWiwOuA6YivkO2UANLIbs15EG-MHtWpuyn1ikO4bh3YKEhDOr1Bz3CaYKYFQDPth0tsjGhSex5wxjTTv4gxlaFRlbiQafmEsGA",
                    "scope": "GOOGLE",
                    "types": [
                        "school",
                        "point_of_interest",
                        "establishment"
                    ],
                    "vicinity": "No. 202, 2nd Cross, Jaibheemanagar, BTM Layout, 1st Stage,, Bengaluru"
                },
                {
                    "geometry": {
                        "location": {
                            "lat": 12.9163187,
                            "lng": 77.612336
                        },
                        "viewport": {
                            "northeast": {
                                "lat": 12.9177280302915,
                                "lng": 77.6136872802915
                            },
                            "southwest": {
                                "lat": 12.9150300697085,
                                "lng": 77.6109893197085
                            }
                        }
                    },
                    "icon": "https://maps.gstatic.com/mapfiles/place_api/icons/atm-71.png",
                    "id": "dda1263d3cf30ca1fb8553ff3d43a49b61021835",
                    "name": "Citibank ATM",
                    "opening_hours": {
                        "open_now": true,
                        "weekday_text": []
                    },
                    "photos": [
                        {
                            "height": 2304,
                            "html_attributions": [
                                "<a href=\"https://maps.google.com/maps/contrib/103267940695519957671/photos\">vaidhynath dubey</a>"
                            ],
                            "photo_reference": "CmRaAAAAgoOGdD6ydGkRXaZvuDcJlYsGdzk9T4iFg8jPFNhb0ACS7GzjlpO7yEc1vyMDB_ZxkMDHk1uvl6pDZwbHorg1JkaKdabrdx-2Md2MIt30CxahIm8k95urH185TArE0qyTEhBwKxiAM2bH4ei54rojqCTwGhR3M7--OvOxRjfJ23r9OyN7YiZzPg",
                            "width": 4096
                        }
                    ],
                    "place_id": "ChIJTXzVFvwUrjsRxYv51nzIEJQ",
                    "rating": 3.2,
                    "reference": "CmRSAAAAzGBueup4tRgiSl5Gq9a5NyHMDHuLgCcRjn59TBv4FMFPhln4wS5mFY1CcRZXUm-ITHtyfO0IRA4XWnydfEZpjK7IxfW_3EzPNRKlP1D_ecKr3e3-d1ZQ-jEIW4_wcRU9EhA98LbVzTUadIokb7mNFHFyGhSzvEeqFjSQIfkFUtXVFIFLfp3UlA",
                    "scope": "GOOGLE",
                    "types": [
                        "atm",
                        "finance",
                        "point_of_interest",
                        "establishment"
                    ],
                    "vicinity": "Shop No. 16, BTM Layout, 2nd Stage, 1st Phase, Bengaluru"
                },
                {
                    "geometry": {
                        "location": {
                            "lat": 12.9204676,
                            "lng": 77.6132909
                        },
                        "viewport": {
                            "northeast": {
                                "lat": 12.9218165802915,
                                "lng": 77.6146398802915
                            },
                            "southwest": {
                                "lat": 12.9191186197085,
                                "lng": 77.61194191970849
                            }
                        }
                    },
                    "icon": "https://maps.gstatic.com/mapfiles/place_api/icons/atm-71.png",
                    "id": "03fbd6dba3889cce01a7894ba5a8f69b16c623f2",
                    "name": "IDBI Bank ATM",
                    "opening_hours": {
                        "open_now": true,
                        "weekday_text": []
                    },
                    "photos": [
                        {
                            "height": 2082,
                            "html_attributions": [
                                "<a href=\"https://maps.google.com/maps/contrib/116869091064335399414/photos\">BK Gajendra</a>"
                            ],
                            "photo_reference": "CmRaAAAAxrAqInwa_VQlmO4F14uQua_qWQcV7EAy-QiOFR_b0iM685uzvVUicktkBIXiSoT20C0bsL1oGOB12f-cm3UNA3_25p4Zp1yg6mYFBunf2LQzJ8Pzzn47LPnc3TamHD_jEhBz_dvD1qxYfK-CyTFjXjr2GhTzNXLXX8swQ_I6ifBOpj92cmztIw",
                            "width": 1485
                        }
                    ],
                    "place_id": "ChIJW0u6Lv8UrjsRLYXzCBN6eVE",
                    "rating": 3.6,
                    "reference": "CmRRAAAAxwPLOso_HW_Ao6UoimYwUYCmzbYzxY-JRN2X5_6LZyvA-BJqQTC7uSG_2RpeoKJ1rLvysHE2O87dAzltpdgD22Lve0_ZmWGkzPSii5lTHadIkBtsSMfbgGIXhWpGpHLnEhAsdOt4pdu7u4h_DBWoSHMXGhSRBWVqlSw_7fa0MjUQFo-O5iabng",
                    "scope": "GOOGLE",
                    "types": [
                        "atm",
                        "finance",
                        "point_of_interest",
                        "establishment"
                    ],
                    "vicinity": "20th Main Road, Madiwala, BTM Layout 1, Bengaluru"
                },
                {
                    "geometry": {
                        "location": {
                            "lat": 12.9230313,
                            "lng": 77.6144664
                        },
                        "viewport": {
                            "northeast": {
                                "lat": 12.9243865302915,
                                "lng": 77.6157979802915
                            },
                            "southwest": {
                                "lat": 12.9216885697085,
                                "lng": 77.6131000197085
                            }
                        }
                    },
                    "icon": "https://maps.gstatic.com/mapfiles/place_api/icons/atm-71.png",
                    "id": "04202500b9ac1734ae24ff0bc8b94268a7cbca33",
                    "name": "HDFC Bank ATM",
                    "opening_hours": {
                        "open_now": true,
                        "weekday_text": []
                    },
                    "photos": [
                        {
                            "height": 3264,
                            "html_attributions": [
                                "<a href=\"https://maps.google.com/maps/contrib/116861322841041331880/photos\">Deepak kushwaha</a>"
                            ],
                            "photo_reference": "CmRaAAAAiIgySZtjLP7B2XKiGAp7Q8fpvStqcsd0cXvw3YBll_8jRlLbZuYGClOl8cwupbqeSgSO0a_KVECw0fL4HAPjMw9HQKY2d3FSgeeJ9yYbBN01YvQdJmTZ1dp99pm4vnuWEhAtGUJW1Q07JZspSSCj9jaFGhR4Z_u4AYvMXerPFUi_kTMAmOAe8w",
                            "width": 2448
                        }
                    ],
                    "place_id": "ChIJ-XnhGVYUrjsRl9RK1ZZ_Pb4",
                    "rating": 2.4,
                    "reference": "CmRSAAAAEPLsu-MCmqhoNEUi06ux3dd07np-eIpBQdF8AhiiUetcGfY1kQs1pSQxhdHYElSI79fau1M6Hp0gyyyWh8ZunOuEdyGPaOxgfwFCDX269kmqe4wP9Lchr8Yz3-9gWZ7XEhClYS7TbbSeHs5XJi1f_I8XGhRuj-iZ96oL38YMpqxB-hweFoAGOQ",
                    "scope": "GOOGLE",
                    "types": [
                        "atm",
                        "bank",
                        "finance",
                        "point_of_interest",
                        "establishment"
                    ],
                    "vicinity": "1224, Maruthi Nagar Main Road, Maruti Nagar, 1st Stage, BTM Layout 1, Bengaluru"
                }
            ],
            "heat": 26.2,
            "lat": 12.92,
            "lng": 77.61
        },
        {
            "details": [
                {
                    "geometry": {
                        "location": {
                            "lat": 12.9159,
                            "lng": 77.6193
                        },
                        "viewport": {
                            "northeast": {
                                "lat": 12.9173401802915,
                                "lng": 77.6206037302915
                            },
                            "southwest": {
                                "lat": 12.9146422197085,
                                "lng": 77.6179057697085
                            }
                        }
                    },
                    "icon": "https://maps.gstatic.com/mapfiles/place_api/icons/atm-71.png",
                    "id": "320a66e8f6041e5b60c29ac2ab80bf944d096e75",
                    "name": "HDFC Bank ATM",
                    "opening_hours": {
                        "open_now": true,
                        "weekday_text": []
                    },
                    "photos": [
                        {
                            "height": 2340,
                            "html_attributions": [
                                "<a href=\"https://maps.google.com/maps/contrib/117017782103728635871/photos\">D&#39;LIFE 360</a>"
                            ],
                            "photo_reference": "CmRaAAAAxBuCCfqpKPsdI-L1Qu3tRlwvUxtjkGMZJ28oeWUf11FWmD_VF77lN99lAPgtHPnajKO9gnYcxbXVWv0_0DZAtcrrF1Vxw9dSPkuUPUiwR3pJU50Chrj1O0rLmDWGTDXnEhDlZlKnUvsiPVUV4VY4nMavGhQityaNYd9PTdhMAMHGQYyAbFGYbQ",
                            "width": 4160
                        }
                    ],
                    "place_id": "ChIJFVxcdfoUrjsRAejF43ttA0o",
                    "rating": 2.8,
                    "reference": "CmRRAAAAxzajx1kvWpRQC-ykqqSwnGnzk1sqiXg4g40JePaOo6Jo_56Gr5gz6bWvG9YpSksDKZ1IVZgVtdDUtYXLmcW9UAkRD4WPWCV4qiegZ1usdPczMoQknlWIhoyyIHhHQYRxEhAFe8PFHXtu-TzUxRpy_YNKGhQuq_V3tVVBMyXlUC_xKB-4qT1bNQ",
                    "scope": "GOOGLE",
                    "types": [
                        "atm",
                        "bank",
                        "finance",
                        "point_of_interest",
                        "establishment"
                    ],
                    "vicinity": "HDFC Bank ATM, 71, 1st Cross, 2nd Stage, BTM Layout, Bengaluru"
                }
            ],
            "heat": 5.6,
            "lat": 12.92,
            "lng": 77.62
        }
    ]
}